psbSDK/__init__.py
psbSDK/movieAPI.py
psbSDK/movieFilters.py
psbSDK/movieSDK.py
psbSDK-1.0.7.dist-info/METADATA
psbSDK-1.0.7.dist-info/WHEEL
psbSDK-1.0.7.dist-info/top_level.txt
psbSDK-1.0.7.dist-info/RECORD
