Metadata-Version: 2.1
Name: psbSDK
Version: 1.0.7
Summary: An SDK for interacting with the Movie API endpoint
Home-page: https://github.com/Sendil239/Sendil_Balan-SDK
Author: Sendil Balan Palanivel
Author-email: sendilbalan@gmail.com
License: UNKNOWN
Platform: UNKNOWN
Classifier: Development Status :: 4 - Beta
Classifier: Intended Audience :: Developers
Classifier: License :: OSI Approved :: MIT License
Classifier: Programming Language :: Python :: 3
Classifier: Programming Language :: Python :: 3.6
Classifier: Programming Language :: Python :: 3.7
Classifier: Programming Language :: Python :: 3.8
Classifier: Programming Language :: Python :: 3.9
Requires-Dist: requests (>=2.26.0)
